openstick/__init__.py
openstick/openstick.py
openstick-1.1.2.dist-info/LICENSE
openstick-1.1.2.dist-info/METADATA
openstick-1.1.2.dist-info/WHEEL
openstick-1.1.2.dist-info/entry_points.txt
openstick-1.1.2.dist-info/top_level.txt
openstick-1.1.2.dist-info/RECORD
