Metadata-Version: 2.1
Name: openstick
Version: 1.1.2
Summary: Because sometimes you don't need a full stack
Home-page: https://github.com/bubu11e/openstick
Author: Julien GIRARD
Author-email: julien.girard.ju@gmail.com
License: GPL3
Platform: UNKNOWN
Requires-Dist: names
